{
  "appIsExample": false,
  "appLayout": {
    "type": "DESKTOP"
  },
  "applicationDetail": {
    "appPositioning": {
      "type": "FIXED"
    },
    "navigationSetting": {
      "colorStyle": "light",
      "itemStyle": "text",
      "logoAssetId": "669bd226f788a72e0d209a28",
      "logoConfiguration": "logoAndApplicationTitle",
      "navStyle": "stacked",
      "orientation": "top",
      "position": "static",
      "showNavbar": false,
      "showSignIn": true
    }
  },
  "applicationVersion": 2,
  "collapseInvisibleWidgets": true,
  "color": "#CCCCCC",
  "evaluationVersion": 2,
  "icon": "calender",
  "pages": [
    {
      "id": "Projects",
      "isDefault": true
    },
    {
      "id": "Generate Form",
      "isDefault": false
    },
    {
      "id": "Generate Overview",
      "isDefault": false
    },
    {
      "id": "Generate Implementation",
      "isDefault": false
    },
    {
      "id": "Generate Tickets",
      "isDefault": false
    },
    {
      "id": "Stakeholder Form",
      "isDefault": false
    }
  ],
  "unpublishedAppLayout": {
    "type": "DESKTOP"
  },
  "unpublishedApplicationDetail": {
    "appPositioning": {
      "type": "FIXED"
    },
    "navigationSetting": {
      "colorStyle": "light",
      "itemStyle": "text",
      "logoAssetId": "669bd226f788a72e0d209a28",
      "logoConfiguration": "logoAndApplicationTitle",
      "navStyle": "stacked",
      "orientation": "top",
      "position": "static",
      "showNavbar": false,
      "showSignIn": true
    }
  }
}