{
  "animateLoading": true,
  "borderRadius": "{{appsmith.theme.borderRadius.appBorderRadius}}",
  "bottomRow": 294,
  "boxShadow": "none",
  "canEscapeKeyClose": true,
  "canOutsideClickClose": false,
  "children": [
    {
      "borderRadius": "{{appsmith.theme.borderRadius.appBorderRadius}}",
      "bottomRow": 270,
      "boxShadow": "{{appsmith.theme.boxShadow.appBoxShadow}}",
      "canExtend": true,
      "detachFromLayout": true,
      "dynamicBindingPathList": [
        {
          "key": "borderRadius"
        },
        {
          "key": "boxShadow"
        }
      ],
      "dynamicHeight": "AUTO_HEIGHT",
      "flexLayers": [],
      "isDisabled": false,
      "isLoading": false,
      "isVisible": true,
      "key": "dlvw5c0cub",
      "leftColumn": 0,
      "maxDynamicHeight": 9000,
      "minDynamicHeight": 4,
      "minHeight": 240,
      "minWidth": 450,
      "mobileBottomRow": 240,
      "mobileLeftColumn": 0,
      "mobileRightColumn": 160.671875,
      "mobileTopRow": 0,
      "needsErrorInfo": false,
      "parentColumnSpace": 1,
      "parentId": "qgqgmb8plk",
      "parentRowSpace": 1,
      "renderMode": "CANVAS",
      "responsiveBehavior": "fill",
      "rightColumn": 160.671875,
      "shouldScrollContents": false,
      "topRow": 0,
      "type": "CANVAS_WIDGET",
      "version": 1,
      "widgetId": "3gtoc5o7mz",
      "widgetName": "Canvas1Copy"
    }
  ],
  "detachFromLayout": true,
  "dynamicBindingPathList": [
    {
      "key": "borderRadius"
    }
  ],
  "dynamicHeight": "AUTO_HEIGHT",
  "dynamicTriggerPathList": [],
  "height": 270,
  "isCanvas": true,
  "isLoading": false,
  "key": "r662k9itcq",
  "leftColumn": 0,
  "maxDynamicHeight": 9000,
  "minDynamicHeight": 24,
  "minHeight": 270,
  "mobileBottomRow": 42,
  "mobileLeftColumn": 0,
  "mobileRightColumn": 13,
  "mobileTopRow": 18,
  "needsErrorInfo": false,
  "parentColumnSpace": 12.359375,
  "parentId": "0",
  "parentRowSpace": 10,
  "renderMode": "CANVAS",
  "rightColumn": 13,
  "shouldScrollContents": true,
  "topRow": 24,
  "type": "MODAL_WIDGET",
  "version": 2,
  "widgetId": "qgqgmb8plk",
  "widgetName": "ErrorModal",
  "width": 456
}